sanic_ext/__init__.py
sanic_ext/bootstrap.py
sanic_ext/config.py
sanic_ext/exceptions.py
sanic_ext/py.typed
sanic_ext/extensions/__init__.py
sanic_ext/extensions/base.py
sanic_ext/extensions/health/__init__.py
sanic_ext/extensions/health/endpoint.py
sanic_ext/extensions/health/extension.py
sanic_ext/extensions/health/monitor.py
sanic_ext/extensions/http/__init__.py
sanic_ext/extensions/http/cors.py
sanic_ext/extensions/http/extension.py
sanic_ext/extensions/http/methods.py
sanic_ext/extensions/injection/__init__.py
sanic_ext/extensions/injection/command_wrapper.py
sanic_ext/extensions/injection/constructor.py
sanic_ext/extensions/injection/extension.py
sanic_ext/extensions/injection/injector.py
sanic_ext/extensions/injection/registry.py
sanic_ext/extensions/logging/__init__.py
sanic_ext/extensions/logging/extension.py
sanic_ext/extensions/logging/extractor.py
sanic_ext/extensions/logging/logger.py
sanic_ext/extensions/openapi/__init__.py
sanic_ext/extensions/openapi/autodoc.py
sanic_ext/extensions/openapi/blueprint.py
sanic_ext/extensions/openapi/builders.py
sanic_ext/extensions/openapi/constants.py
sanic_ext/extensions/openapi/definitions.py
sanic_ext/extensions/openapi/extension.py
sanic_ext/extensions/openapi/openapi.py
sanic_ext/extensions/openapi/types.py
sanic_ext/extensions/openapi/ui/redoc.html
sanic_ext/extensions/openapi/ui/swagger.html
sanic_ext/extensions/templating/__init__.py
sanic_ext/extensions/templating/engine.py
sanic_ext/extensions/templating/extension.py
sanic_ext/extensions/templating/render.py
sanic_ext/extras/__init__.py
sanic_ext/extras/request.py
sanic_ext/extras/serializer/__init__.py
sanic_ext/extras/serializer/decorator.py
sanic_ext/extras/validation/__init__.py
sanic_ext/extras/validation/check.py
sanic_ext/extras/validation/clean.py
sanic_ext/extras/validation/decorator.py
sanic_ext/extras/validation/schema.py
sanic_ext/extras/validation/setup.py
sanic_ext/extras/validation/validators.py
sanic_ext/utils/__init__.py
sanic_ext-25.12.0.dist-info/licenses/LICENSE
sanic_ext-25.12.0.dist-info/METADATA
sanic_ext-25.12.0.dist-info/WHEEL
sanic_ext-25.12.0.dist-info/top_level.txt
sanic_ext-25.12.0.dist-info/RECORD
